sqlark/__init__.py
sqlark/column_definition.py
sqlark/command.py
sqlark/count.py
sqlark/delete.py
sqlark/insert.py
sqlark/join.py
sqlark/logger.py
sqlark/postgres_config.py
sqlark/response_formatters.py
sqlark/select.py
sqlark/update.py
sqlark/utilities.py
sqlark/where.py
sqlark-1.1.0.dist-info/LICENSE
sqlark-1.1.0.dist-info/METADATA
sqlark-1.1.0.dist-info/WHEEL
sqlark-1.1.0.dist-info/RECORD
