Metadata-Version: 2.1
Name: sqlark
Version: 1.1.0
Summary: A lightweight Non-ORM with a builder pattern for querying a postgres database
Author: Joshua Shapiro
Author-email: jshapiro@meadowlarkengineering.com
Requires-Python: >=3.10,<4.0
Classifier: Programming Language :: Python :: 3
Classifier: Programming Language :: Python :: 3.10
Classifier: Programming Language :: Python :: 3.11
Classifier: Programming Language :: Python :: 3.12
Classifier: Programming Language :: Python :: 3.13
Requires-Dist: boto3 (>=1.35.29,<2.0.0)
Requires-Dist: psycopg2-binary (>=2.9.5,<3.0.0)
